{
  "seed_version": 2,
  "status": "milestone-b-backbone",
  "owner_module": "auth-kernel",
  "catalog_name": "decision_reason_taxonomy",
  "reason_codes": [
    {
      "reason_code": "actor_unresolved",
      "description": "Canonical actor could not be resolved from ingress evidence."
    },
    {
      "reason_code": "actor_ambiguous",
      "description": "Multiple canonical actors matched the supplied ingress identity evidence."
    },
    {
      "reason_code": "actor_inactive",
      "description": "Canonical actor exists but is not in an active lifecycle state."
    },
    {
      "reason_code": "binding_missing",
      "description": "Required role or scope binding does not exist for the resolved actor."
    },
    {
      "reason_code": "scope_unbound",
      "description": "Required scope binding is missing or still pending confirmation."
    },
    {
      "reason_code": "invalid_scope_selection",
      "description": "Requested scope is outside the actor's granted scope bindings."
    },
    {
      "reason_code": "tenant_mismatch",
      "description": "Scope binding tenant does not match the actor tenant and must fail closed."
    },
    {
      "reason_code": "capability_not_granted",
      "description": "Requested capability is not granted to the current binding snapshot."
    },
    {
      "reason_code": "missing_decision_ref",
      "description": "Protected capability evaluation failed closed because no decision_ref was supplied."
    },
    {
      "reason_code": "manual_review_needed",
      "description": "Request must move to explicit escalation or review flow."
    }
  ]
}
